IABT/InxioManifest.vsp
IABT/__init__.py
IABT/build.py
IABT/file_control.py
IABT/generate_path.py
IABT/iabt.py
IABT/json_control.py
IABT/data/EventActivity.java
IABT/data/FormalActivity.java
IABT/data/PermissionActivity.java
IABT/data/VDialogInterface.java
IABT/data/VLocationListener.java
IABT/data/VOnClickListener.java
IABT/data/VSensorEventListener.java
IABT/data/app_build.gradle
IABT/data/project_build.gradle
IABT/inxio_core/__init__.py
IABT/inxio_core/Inxio/__init__.py
IABT/inxio_core/Inxio/file_type.py
IABT/inxio_core/Inxio/global_var.py
IABT/inxio_core/Inxio/android/__init__.py
IABT/inxio_core/Inxio/android/APP/__init__.py
IABT/inxio_core/Inxio/android/APP/app.py
IABT/inxio_core/Inxio/android/APP/permission.py
IABT/inxio_core/Inxio/android/core_components/Activity.py
IABT/inxio_core/Inxio/android/core_components/Bundle.py
IABT/inxio_core/Inxio/android/core_components/EventProcess.py
IABT/inxio_core/Inxio/android/core_components/Fragment.py
IABT/inxio_core/Inxio/android/core_components/Intent.py
IABT/inxio_core/Inxio/android/core_components/LocationManager.py
IABT/inxio_core/Inxio/android/core_components/NotificationManager.py
IABT/inxio_core/Inxio/android/core_components/PendingIntent.py
IABT/inxio_core/Inxio/android/core_components/SensorManager.py
IABT/inxio_core/Inxio/android/core_components/Service.py
IABT/inxio_core/Inxio/android/core_components/View.py
IABT/inxio_core/Inxio/android/core_components/View_Listeners.py
IABT/inxio_core/Inxio/android/core_components/XMLGenerator.py
IABT/inxio_core/Inxio/android/core_components/__init__.py
IABT/inxio_core/Inxio/android/executable/ExecutionBlock.py
IABT/inxio_core/Inxio/android/executable/__init__.py
IABT/inxio_core/Inxio/android/ui/__init__.py
IABT/inxio_core/Inxio/android/ui/Element/AlertDialog.py
IABT/inxio_core/Inxio/android/ui/Element/Text.py
IABT/inxio_core/Inxio/android/ui/Element/Toast.py
IABT/inxio_core/Inxio/android/ui/Element/__init__.py
IABT/inxio_core/Inxio/android/ui/Layout/FrameLayout.py
IABT-1.3.2.dist-info/METADATA
IABT-1.3.2.dist-info/WHEEL
IABT-1.3.2.dist-info/top_level.txt
IABT-1.3.2.dist-info/RECORD
