Metadata-Version: 2.1
Name: IABT
Version: 1.3.2
Summary: IABT is a tool to build your Inxio project.It can create a project and build a project.
Home-page: UNKNOWN
Author: cemeye
Author-email: caomingyang2022@163.com
License: MIT
Platform: UNKNOWN
Classifier: Development Status :: 1 - Planning
Classifier: Intended Audience :: Developers
Classifier: Programming Language :: Python :: 3
Classifier: Operating System :: Unix
Classifier: Operating System :: MacOS :: MacOS X
Classifier: Operating System :: Microsoft :: Windows
Requires-Dist: colorama (>=0.4.6)
